tf_video/__init__.py
tf_video/main.py
tf_video/utils/__init__.py
tf_video/utils/contrast_utils.py
tf_video/utils/flip_utils.py
tf_video/utils/rotation_utils.py
tf_video/utils/zoom_utils.py
tf_video-0.0.7.dist-info/LICENSE
tf_video-0.0.7.dist-info/METADATA
tf_video-0.0.7.dist-info/WHEEL
tf_video-0.0.7.dist-info/top_level.txt
tf_video-0.0.7.dist-info/RECORD
