Metadata-Version: 2.1
Name: tf-video
Version: 0.0.7
Summary: A library providing tools for working with videos in TensorFlow.
Home-page: https://github.com/jegork/tf-video-preprocessing
Author: Jegor Kitskerkin
Author-email: jegor.kitskerkin@gmail.com
License: MIT License
Platform: UNKNOWN
License-File: LICENSE
Requires-Dist: tensorflow (>=2.8.0)
Requires-Dist: keras (>=2.8.0)
Requires-Dist: numpy
